MANIFEST.in
README.md
requirements.txt
setup.cfg
setup.py
sixecho/__init__.py
sixecho/base.py
sixecho/chain.py
sixecho/client.py
sixecho/echo_util.py
sixecho/image_digest.py
sixecho/text_digest.py
sixecho.egg-info/PKG-INFO
sixecho.egg-info/SOURCES.txt
sixecho.egg-info/dependency_links.txt
sixecho.egg-info/requires.txt
sixecho.egg-info/top_level.txt
sixecho/tests/__init__.py