Metadata-Version: 2.1
Name: sixecho
Version: 1.3.0
Summary: digital contents
Home-page: https://github.com/thesixnetwork/SIXEcho
Author: six.network
Author-email: dev-lead@six.network
License: MIT
Platform: UNKNOWN
